fpga/src/hdl/sensors/sensor_hub.vhd
library IEEE;
use IEEE.STD_LOGIC_1164.ALL;
use IEEE.NUMERIC_STD.ALL;
use work.nebkiso_pkg.all;

entity sensor_hub is
    port (
        -- System signals
        clk           : in  std_logic;
        rst           : in  std_logic;
        
        -- I2C interfaces for sensors
        scl           : inout std_logic_vector(3 downto 0);
        sda           : inout std_logic_vector(3 downto 0);
        
        -- ADC interfaces
        adc_spi_sclk  : out std_logic;
        adc_spi_mosi  : out std_logic;
        adc_spi_miso  : in  std_logic;
        adc_spi_cs_n  : out std_logic_vector(7 downto 0);
        
        -- Processed sensor data outputs
        voc_data      : out std_logic_vector(11 downto 0);
        aq_data       : out std_logic_vector(11 downto 0);
        pressure_data : out std_logic_vector(11 downto 0);
        temp_data     : out std_logic_vector(11 downto 0);
        flow_data     : out std_logic_vector(7 downto 0);
        
        -- Calibration interface
        cal_mode      : in  std_logic;
        cal_data      : in  std_logic_vector(15 downto 0);
        cal_addr      : in  std_logic_vector(7 downto 0);
        cal_wr        : in  std_logic;
        
        -- Status outputs
        sensor_status : out std_logic_vector(7 downto 0);
        error_flags   : out std_logic_vector(7 downto 0)
    );
end entity sensor_hub;

architecture behavioral of sensor_hub is
    -- State machine type definition
    type sensor_state_type is (
        INIT,
        CALIBRATE,
        SAMPLE,
        PROCESS_DATA  -- Changed from PROCESS which is a keyword
    );
    
    -- Internal signals
    signal current_state : sensor_state_type;
    
    -- Calibration data storage
    type cal_data_array is array (0 to 255) of std_logic_vector(15 downto 0);
    signal cal_storage : cal_data_array;
    
    -- Sensor sampling counters
    signal sample_counter : unsigned(15 downto 0);
    signal sensor_select : unsigned(2 downto 0);
    
    -- Moving average buffers
    type avg_buffer is array (0 to 7) of unsigned(15 downto 0);
    signal voc_buffer : avg_buffer;
    signal aq_buffer : avg_buffer;
    signal pressure_buffer : avg_buffer;
    signal temp_buffer : avg_buffer;
    
    -- ADC interface signals
    signal adc_data : std_logic_vector(11 downto 0);
    signal adc_valid : std_logic;
    signal adc_channel : unsigned(2 downto 0);
    
begin
    -- ADC read function implementation
    adc_read_proc: process(clk)
        variable adc_result : std_logic_vector(11 downto 0);
    begin
        if rising_edge(clk) then
            if rst = '1' then
                adc_data <= (others => '0');
                adc_valid <= '0';
            else
                -- Simple test pattern for simulation
                adc_result := std_logic_vector(to_unsigned(to_integer(adc_channel) * 100, 12));
                adc_data <= adc_result;
                adc_valid <= '1';
            end if;
        end if;
    end process adc_read_proc;

    -- Main control process
    main_proc: process(clk)
        variable avg_sum : unsigned(18 downto 0);
    begin
        if rising_edge(clk) then
            if rst = '1' then
                current_state <= INIT;
                sensor_select <= (others => '0');
                sample_counter <= (others => '0');
                sensor_status <= (others => '0');
                error_flags <= (others => '0');
                voc_data <= (others => '0');
                aq_data <= (others => '0');
                pressure_data <= (others => '0');
                temp_data <= (others => '0');
                flow_data <= (others => '0');
            else
                case current_state is
                    when INIT =>
                        -- Initialize sensors
                        if sensor_select = 7 then
                            current_state <= CALIBRATE;
                            sensor_select <= (others => '0');
                        else
                            sensor_select <= sensor_select + 1;
                        end if;
                        
                    when CALIBRATE =>
                        -- Apply calibration data
                        if cal_mode = '1' and cal_wr = '1' then
                            cal_storage(to_integer(unsigned(cal_addr))) <= cal_data;
                        end if;
                        
                        if sensor_select = 7 then
                            current_state <= SAMPLE;
                            sensor_select <= (others => '0');
                        else
                            sensor_select <= sensor_select + 1;
                        end if;
                        
                    when SAMPLE =>
                        -- Sample each sensor type
                        case to_integer(sensor_select) is
                            when 0 => -- VOC
                                if adc_valid = '1' then
                                    voc_buffer(to_integer(sample_counter(2 downto 0))) <= 
                                        unsigned(cal_storage(0)) * unsigned(adc_data);
                                end if;
                            when 1 => -- Air Quality
                                if adc_valid = '1' then
                                    aq_buffer(to_integer(sample_counter(2 downto 0))) <= 
                                        unsigned(cal_storage(1)) * unsigned(adc_data);
                                end if;
                            when 2 => -- Pressure
                                if adc_valid = '1' then
                                    pressure_buffer(to_integer(sample_counter(2 downto 0))) <= 
                                        unsigned(cal_storage(2)) * unsigned(adc_data);
                                end if;
                            when 3 => -- Temperature
                                if adc_valid = '1' then
                                    temp_buffer(to_integer(sample_counter(2 downto 0))) <= 
                                        unsigned(cal_storage(3)) * unsigned(adc_data);
                                end if;
                            when others =>
                                null;
                        end case;
                        
                        if sensor_select = 3 then
                            current_state <= PROCESS_DATA;
                            sensor_select <= (others => '0');
                        else
                            sensor_select <= sensor_select + 1;
                        end if;
                        
                    when PROCESS_DATA =>
                        -- Calculate moving averages
                        avg_sum := (others => '0');
                        
                        -- VOC average
                        for i in 0 to 7 loop
                            avg_sum := avg_sum + voc_buffer(i);
                        end loop;
                        voc_data <= std_logic_vector(avg_sum(18 downto 7));
                        
                        -- Reset for next sampling cycle
                        sample_counter <= sample_counter + 1;
                        current_state <= SAMPLE;
                        
                end case;
            end if;
        end if;
    end process main_proc;

end architecture behavioral;

fpga/src/testbench/sensor_hub_tb.vhd
library IEEE;
use IEEE.STD_LOGIC_1164.ALL;
use IEEE.NUMERIC_STD.ALL;
use work.nebkiso_pkg.all;
use work.nebkiso_tb_pkg.all;

entity sensor_hub_tb is
end sensor_hub_tb;

architecture behavioral of sensor_hub_tb is
    -- Clock and reset
    signal clk : std_logic := '0';
    signal rst : std_logic := '1';
    
    -- I2C interfaces
    signal scl : std_logic_vector(3 downto 0);
    signal sda : std_logic_vector(3 downto 0);
    
    -- SPI interfaces
    signal adc_spi_sclk : std_logic;
    signal adc_spi_mosi : std_logic;
    signal adc_spi_miso : std_logic := '0';
    signal adc_spi_cs_n : std_logic_vector(7 downto 0);
    
    -- Sensor data outputs
    signal voc_data : std_logic_vector(11 downto 0);
    signal aq_data : std_logic_vector(11 downto 0);
    signal pressure_data : std_logic_vector(11 downto 0);
    signal temp_data : std_logic_vector(11 downto 0);
    signal flow_data : std_logic_vector(7 downto 0);
    
    -- Calibration interface
    signal cal_mode : std_logic := '0';
    signal cal_data : std_logic_vector(15 downto 0) := (others => '0');
    signal cal_addr : std_logic_vector(7 downto 0) := (others => '0');
    signal cal_wr : std_logic := '0';
    
    -- Status outputs
    signal sensor_status : std_logic_vector(7 downto 0);
    signal error_flags : std_logic_vector(7 downto 0);

begin
    -- Clock generation
    clk <= not clk after CLK_PERIOD/2;
    
    -- DUT instantiation
    DUT: entity work.sensor_hub
    port map (
        clk => clk,
        rst => rst,
        scl => scl,
        sda => sda,
        adc_spi_sclk => adc_spi_sclk,
        adc_spi_mosi => adc_spi_mosi,
        adc_spi_miso => adc_spi_miso,
        adc_spi_cs_n => adc_spi_cs_n,
        voc_data => voc_data,
        aq_data => aq_data,
        pressure_data => pressure_data,
        temp_data => temp_data,
        flow_data => flow_data,
        cal_mode => cal_mode,
        cal_data => cal_data,
        cal_addr => cal_addr,
        cal_wr => cal_wr,
        sensor_status => sensor_status,
        error_flags => error_flags
    );
    
    -- Test process
    test_proc: process
    begin
        -- Initialize
        report "Starting sensor hub tests...";
        wait for CLK_PERIOD * 2;
        
        -- Release reset
        rst <= '0';
        wait for CLK_PERIOD * 2;
        
        -- Test Case 1: Normal Operation
        report "Test Case 1: Normal Operation";
        adc_spi_miso <= '1';  -- Simulate ADC data
        wait for CLK_PERIOD * 100;
        
        -- Test Case 2: Calibration Mode
        report "Test Case 2: Calibration Mode";
        cal_mode <= '1';
        cal_addr <= x"00";
        cal_data <= x"1234";
        cal_wr <= '1';
        wait for CLK_PERIOD * 10;
        cal_wr <= '0';
        wait for CLK_PERIOD * 100;
        
        -- Test Case 3: Error Injection
        report "Test Case 3: Error Injection";
        adc_spi_miso <= '0';  -- Simulate ADC error
        wait for CLK_PERIOD * 100;
        
        -- Test Case 4: Recovery
        report "Test Case 4: Recovery";
        adc_spi_miso <= '1';
        cal_mode <= '0';
        wait for CLK_PERIOD * 100;
        
        -- End simulation
        report "Sensor hub tests completed";
        wait;
    end process;
    
    -- I2C response simulation process
    i2c_sim: process
    begin
        -- Pull-up resistors simulation
        scl <= (others => 'H');
        sda <= (others => 'H');
        
        wait for CLK_PERIOD;
        
        -- Simulate I2C responses
        loop
            if scl(0) = '0' then
                sda(0) <= '0';  -- ACK
            end if;
            wait for I2C_PERIOD;
        end loop;
    end process;
    
end behavioral;

fpga/sim/sensor_hub.vcd
$date
  Thu Nov 21 23:46:34 2024
$end
$version
  GHDL v0
$end
$timescale
  1 fs
$end
$scope module standard $end
$upscope $end
$scope module textio $end
$upscope $end
$scope module std_logic_1164 $end
$upscope $end
$scope module numeric_std $end
$upscope $end
$scope module nebkiso_pkg $end
$upscope $end
$scope module nebkiso_tb_pkg $end
$upscope $end
$scope module sensor_hub_tb $end
$var reg 1 ! clk $end
$var reg 1 " rst $end
$var reg 4 # scl[3:0] $end
$var reg 4 $ sda[3:0] $end
$var reg 1 % adc_spi_sclk $end
$var reg 1 & adc_spi_mosi $end
$var reg 1 ' adc_spi_miso $end
$var reg 8 ( adc_spi_cs_n[7:0] $end
$var reg 12 ) voc_data[11:0] $end
$var reg 12 * aq_data[11:0] $end
$var reg 12 + pressure_data[11:0] $end
$var reg 12 , temp_data[11:0] $end
$var reg 8 - flow_data[7:0] $end
$var reg 1 . cal_mode $end
$var reg 16 / cal_data[15:0] $end
$var reg 8 0 cal_addr[7:0] $end
$var reg 1 1 cal_wr $end
$var reg 8 2 sensor_status[7:0] $end
$var reg 8 3 error_flags[7:0] $end
$scope module dut $end
$var reg 1 4 clk $end
$var reg 1 5 rst $end
$var reg 4 6 scl[3:0] $end
$var reg 4 7 sda[3:0] $end
$var reg 1 8 adc_spi_sclk $end
$var reg 1 9 adc_spi_mosi $end
$var reg 1 : adc_spi_miso $end
$var reg 8 ; adc_spi_cs_n[7:0] $end
$var reg 12 < voc_data[11:0] $end
$var reg 12 = aq_data[11:0] $end
$var reg 12 > pressure_data[11:0] $end
$var reg 12 ? temp_data[11:0] $end
$var reg 8 @ flow_data[7:0] $end
$var reg 1 A cal_mode $end
$var reg 16 B cal_data[15:0] $end
$var reg 8 C cal_addr[7:0] $end
$var reg 1 D cal_wr $end
$var reg 8 E sensor_status[7:0] $end
$var reg 8 F error_flags[7:0] $end
$comment current_state is not handled $end
$comment cal_storage is not handled $end
$var reg 16 G sample_counter[15:0] $end
$var reg 3 H sensor_select[2:0] $end
$comment voc_buffer is not handled $end
$comment aq_buffer is not handled $end
$comment pressure_buffer is not handled $end
$comment temp_buffer is not handled $end
$var reg 12 I adc_data[11:0] $end
$var reg 1 J adc_valid $end
$var reg 3 K adc_channel[2:0] $end
$upscope $end
$upscope $end
$enddefinitions $end
#0
0!
1"
bHHHH #
bHHHH $
U%
U&
0'
bUUUUUUUU (
bUUUUUUUUUUUU )
bUUUUUUUUUUUU *
bUUUUUUUUUUUU +
bUUUUUUUUUUUU ,
bUUUUUUUU -
0.
b0000000000000000 /
b00000000 0
01
bUUUUUUUU 2
bUUUUUUUU 3
04
15
bHHHH 6
bHHHH 7
U8
U9
0:
bUUUUUUUU ;
bUUUUUUUUUUUU <
bUUUUUUUUUUUU =
bUUUUUUUUUUUU >
bUUUUUUUUUUUU ?
bUUUUUUUU @
0A
b0000000000000000 B
b00000000 C
0D
bUUUUUUUU E
bUUUUUUUU F
bUUUUUUUUUUUUUUUU G
bUUU H
bUUUUUUUUUUUU I
UJ
bUUU K
#5000000
1!
b000000000000 )
b000000000000 *
b000000000000 +
b000000000000 ,
b00000000 -
b00000000 2
b00000000 3
14
b000000000000 <
b000000000000 =
b000000000000 >
b000000000000 ?
b00000000 @
b00000000 E
b00000000 F
b0000000000000000 G
b000 H
b000000000000 I
0J
#10000000
0!
04
#15000000
1!
14
#20000000
0!
0"
04
05
#25000000
1!
14
b001 H
1J
#30000000
0!
04
#35000000
1!
14
b010 H
#40000000
0!
1'
04
1:
#45000000
1!
14
b011 H
#50000000
0!
04
#55000000
1!
14
b100 H
#60000000
0!
04
#65000000
1!
14
b101 H
#70000000
0!
04
#75000000
1!
14
b110 H
#80000000
0!
04
#85000000
1!
14
b111 H
#90000000
0!
04
#95000000
1!
14
b000 H
#100000000
0!
04
#105000000
1!
14
b001 H
#110000000
0!
04
#115000000
1!
14
b010 H
#120000000
0!
04
#125000000
1!
14
b011 H
#130000000
0!
04
#135000000
1!
14
b100 H
#140000000
0!
04
#145000000
1!
14
b101 H
#150000000
0!
04
#155000000
1!
14
b110 H
#160000000
0!
04
#165000000
1!
14
b111 H
#170000000
0!
04
#175000000
1!
14
b000 H
